dayone_to_obsidian/__init__.py
dayone_to_obsidian/cli.py
dayone_to_obsidian/helpers.py
dayone_to_obsidian/models.py
dayone_to_obsidian/options.py
dayone_to_obsidian/py.typed
dayone_to_obsidian/version.py
dayone_to_obsidian/processors/__init__.py
dayone_to_obsidian/processors/entry.py
dayone_to_obsidian/processors/journal.py
dayone_to_obsidian/processors/utils.py
dayone_to_obsidian/processors/media/__init__.py
dayone_to_obsidian/processors/media/audio.py
dayone_to_obsidian/processors/media/base.py
dayone_to_obsidian/processors/media/pdf.py
dayone_to_obsidian/processors/media/photo.py
dayone_to_obsidian/processors/media/video.py
dayone_to_obsidian-0.5.5.dist-info/METADATA
dayone_to_obsidian-0.5.5.dist-info/WHEEL
dayone_to_obsidian-0.5.5.dist-info/entry_points.txt
dayone_to_obsidian-0.5.5.dist-info/licenses/LICENSE
dayone_to_obsidian-0.5.5.dist-info/RECORD
