Metadata-Version: 2.4
Name: dayone-to-obsidian
Version: 0.5.5
Summary: Convert a JSON export from Day One into individual notes for Obsidian.
Project-URL: Homepage, https://github.com/kulapard/dayone-to-obsidian
Project-URL: Documentation, https://github.com/kulapard/dayone-to-obsidian
Project-URL: Repository, https://github.com/kulapard/dayone-to-obsidian
Author-email: Taras Drapalyuk <taras@drapalyuk.com>
License-Expression: MIT
License-File: LICENSE
Classifier: Development Status :: 4 - Beta
Classifier: Environment :: Web Environment
Classifier: Intended Audience :: Developers
Classifier: Intended Audience :: Information Technology
Classifier: Intended Audience :: System Administrators
Classifier: License :: OSI Approved :: MIT License
Classifier: Operating System :: OS Independent
Classifier: Programming Language :: Python
Classifier: Programming Language :: Python :: 3
Classifier: Programming Language :: Python :: 3 :: Only
Classifier: Programming Language :: Python :: 3.10
Classifier: Programming Language :: Python :: 3.11
Classifier: Programming Language :: Python :: 3.12
Classifier: Programming Language :: Python :: 3.13
Classifier: Topic :: Internet
Classifier: Topic :: Software Development
Classifier: Topic :: Software Development :: Libraries
Classifier: Topic :: Software Development :: Libraries :: Python Modules
Classifier: Typing :: Typed
Requires-Python: >=3.10
Requires-Dist: click<9.0.0,>=8.1.7
Requires-Dist: pydantic<3.0.0,>=2.5.2
Requires-Dist: python-dateutil<3.0.0,>=2.8.2
